griffe_pydantic-1.1.8.dist-info/METADATA
griffe_pydantic-1.1.8.dist-info/WHEEL
griffe_pydantic-1.1.8.dist-info/entry_points.txt
griffe_pydantic-1.1.8.dist-info/licenses/LICENSE
griffe_pydantic/__init__.py
griffe_pydantic/_internal/__init__.py
griffe_pydantic/_internal/common.py
griffe_pydantic/_internal/debug.py
griffe_pydantic/_internal/dynamic.py
griffe_pydantic/_internal/extension.py
griffe_pydantic/_internal/static.py
griffe_pydantic/common.py
griffe_pydantic/dynamic.py
griffe_pydantic/extension.py
griffe_pydantic/py.typed
griffe_pydantic/static.py
griffe_pydantic/templates/material/_base/pydantic_model.html.jinja
griffe_pydantic/templates/material/pydantic_model.html.jinja
griffe_pydantic-1.1.8.dist-info/RECORD
