Metadata-Version: 2.4
Name: griffe-pydantic
Version: 1.1.8
Summary: Griffe extension for Pydantic.
Author-Email: =?utf-8?q?Timoth=C3=A9e_Mazzucotelli?= <dev@pawamoy.fr>
License-Expression: ISC
License-File: LICENSE
Classifier: Development Status :: 4 - Beta
Classifier: Intended Audience :: Developers
Classifier: Programming Language :: Python
Classifier: Programming Language :: Python :: 3
Classifier: Programming Language :: Python :: 3 :: Only
Classifier: Programming Language :: Python :: 3.9
Classifier: Programming Language :: Python :: 3.10
Classifier: Programming Language :: Python :: 3.11
Classifier: Programming Language :: Python :: 3.12
Classifier: Programming Language :: Python :: 3.13
Classifier: Programming Language :: Python :: 3.14
Classifier: Topic :: Documentation
Classifier: Topic :: Software Development
Classifier: Topic :: Utilities
Classifier: Typing :: Typed
Project-URL: Homepage, https://mkdocstrings.github.io/griffe-pydantic
Project-URL: Documentation, https://mkdocstrings.github.io/griffe-pydantic
Project-URL: Changelog, https://mkdocstrings.github.io/griffe-pydantic/changelog
Project-URL: Repository, https://github.com/mkdocstrings/griffe-pydantic
Project-URL: Issues, https://github.com/mkdocstrings/griffe-pydantic/issues
Project-URL: Discussions, https://github.com/mkdocstrings/griffe-pydantic/discussions
Project-URL: Gitter, https://gitter.im/mkdocstrings/griffe-pydantic
Project-URL: Funding, https://github.com/sponsors/pawamoy
Requires-Python: >=3.9
Requires-Dist: griffe>=1.14
